et_dot/.orig.__init__.py
et_dot/__init__.py
et_dot/cli_dotfiles.py
et_dot/cpp_dotc/CMakeLists.txt
et_dot/cpp_dotc/dotc.cpp
et_dot/cpp_dotc/dotc.rst
et_dot/f90_dotf/CMakeLists.txt
et_dot/f90_dotf/dotf.f90
et_dot/f90_dotf/dotf.rst
et_dot-0.0.1.dist-info/entry_points.txt
et_dot-0.0.1.dist-info/LICENSE
et_dot-0.0.1.dist-info/WHEEL
et_dot-0.0.1.dist-info/METADATA
et_dot-0.0.1.dist-info/RECORD
